README.txt
setup.py
xmlpolymerase/__init__.py
xmlpolymerase/deserializer.py
xmlpolymerase/exceptions.py
xmlpolymerase/odict.py
xmlpolymerase/serializer.py
xmlpolymerase/tests.py
xmlpolymerase.egg-info/PKG-INFO
xmlpolymerase.egg-info/SOURCES.txt
xmlpolymerase.egg-info/dependency_links.txt
xmlpolymerase.egg-info/entry_points.txt
xmlpolymerase.egg-info/namespace_packages.txt
xmlpolymerase.egg-info/not-zip-safe
xmlpolymerase.egg-info/requires.txt
xmlpolymerase.egg-info/top_level.txt
