Metadata-Version: 1.0
Name: xmlpolymerase
Version: 1.1
Summary: XML (de-) serializer for simple python structures.
Home-page: https://svn.plone.org/svn/collective/xmlpolymerase
Author: Jens Klein
Author-email: jens@bluedynamics.com
License: GPL
Platform: UNKNOWN
Classifier: Framework :: Plone
Classifier: Framework :: Zope2
Classifier: Framework :: Zope3
Classifier: Programming Language :: Python
Classifier: Topic :: Software Development :: Libraries :: Python Modules
